blockchain_scalpel/__init__.py
blockchain_scalpel/blockchain-parser.py
blockchain_scalpel/cli.py
blockchain_scalpel-2.0.3.dist-info/licenses/LICENSE
blockchain_scalpel-2.0.3.dist-info/METADATA
blockchain_scalpel-2.0.3.dist-info/WHEEL
blockchain_scalpel-2.0.3.dist-info/entry_points.txt
blockchain_scalpel-2.0.3.dist-info/top_level.txt
blockchain_scalpel-2.0.3.dist-info/RECORD
