Metadata-Version: 2.4
Name: blockchain-scalpel
Version: 2.0.3
Summary: Blockchain parser (source-available). Free for non-commercial use with attribution. Commercial & SaaS licenses available.
Author: Denis Leonov
License-Expression: LicenseRef-Blockchain-Scalpel
Project-URL: Homepage, https://github.com/ragestack/blockchain-parser
Classifier: Programming Language :: Python :: 3
Requires-Python: >=3.9
License-File: LICENSE
Dynamic: license-file
